{"command_name": "betatest", "description": "A test command", "usage": "betatest", "function": "betatest", "function_file_location": "C:\\Users\\PC\\Desktop\\Scripts\\px\\betatest.txt"}{"command_name": "betateest", "description": "betatest", "usage": "betatest", "function": "beta", "function_file_location": "C:\\Users\\PC\\Desktop\\Scripts\\px\\betatest.txt"}{"command_name": "betatestInstall", "description": "beta test installer", "usage": "betatestInstall", "function": "beta", "function_file_location": "C:\\Users\\PC\\Desktop\\Scripts\\px\\betatest.txt"}{"command_name": "beta", "description": "beta", "usage": "beta", "function": "beta", "function_file_location": "C:\\Users\\PC\\Desktop\\Scripts\\px\\betatest.txt"}{"command_name": "beta", "description": "beta", "usage": "beta", "function": "beta", "function_file_location": "C:\\Users\\PC\\Desktop\\Scripts\\px\\betatest.txt"}{"command_name": "beta", "description": "beta", "usage": "betaa", "function": "beta", "function_file_location": "C:\\Users\\PC\\Desktop\\Scripts\\px\\betatest.txt"}{"command_name": "beta", "description": "beta", "usage": "beta", "function": "beta", "function_file_location": "C:\\Users\\PC\\Desktop\\Scripts\\px\\betatest.txt"}{"command_name": "beta", "description": "beta", "usage": "beta", "function": "beta", "function_file_location": "C:\\Users\\PC\\Desktop\\Scripts\\px\\betatest.txt"}{"command_name": "beta", "description": "beta", "usage": "beta", "function": "beta", "function_file_location": "C:\\Users\\PC\\Desktop\\Scripts\\px\\betatest.txt"}{"command_name": "beta", "description": "beta", "usage": "beta", "function": "self.beta", "function_file_location": "C:\\Users\\PC\\Desktop\\Scripts\\px\\betatest.txt"}{"command_name": "merhaba", "description": "merhaba", "usage": "merhaba", "function": "merhaba", "function_file_location": "C:\\Users\\PC\\Desktop\\Scripts\\px\\betatest.txt"}